glymur/__init__.py
glymur/_core_converter.py
glymur/_iccprofile.py
glymur/codestream.py
glymur/command_line.py
glymur/config.py
glymur/core.py
glymur/jp2box.py
glymur/jp2k.py
glymur/jp2kr.py
glymur/jpeg.py
glymur/options.py
glymur/tiff.py
glymur/version.py
glymur/data/__init__.py
glymur/data/goodstuff.j2k
glymur/data/heliov.jpx
glymur/data/nemo.jp2
glymur/lib/__init__.py
glymur/lib/_tiff.py
glymur/lib/openjp2.py
glymur/lib/tiff.py
glymur-0.14.6.dist-info/licenses/LICENSE.txt
glymur-0.14.6.dist-info/METADATA
glymur-0.14.6.dist-info/WHEEL
glymur-0.14.6.dist-info/entry_points.txt
glymur-0.14.6.dist-info/top_level.txt
glymur-0.14.6.dist-info/RECORD
